tnt_python/__init__.py
tnt_python/data.py
tnt_python/enums.py
tnt_python/file_creator.py
tnt_python/services.py
tnt_python/types.py
tnt_python/utils.py
tnt_python-0.2.1.dist-info/LICENSE
tnt_python-0.2.1.dist-info/WHEEL
tnt_python-0.2.1.dist-info/METADATA
tnt_python-0.2.1.dist-info/RECORD
