Metadata-Version: 2.1
Name: tnt-python
Version: 0.2.1
Summary: Telegram notification tool
Home-page: https://github.com/watchmanix/tnt-python
License: MIT
Keywords: python,telegram
Author: axeman
Author-email: axeman.ofic@gmail.com
Maintainer: axeman
Maintainer-email: axeman.ofic@gmail.com
Requires-Python: >=3.10,<4.0
Classifier: Development Status :: 5 - Production/Stable
Classifier: License :: OSI Approved :: MIT License
Classifier: Programming Language :: Python :: 3
Classifier: Programming Language :: Python :: 3.10
Requires-Dist: httpx (>=0.23.0,<0.24.0)
Project-URL: Repository, https://github.com/watchmanix/tnt-python
